wonderpatch/__init__.py
wonderpatch/wonderpatch.py
wonderpatch-0.1.0.dist-info/LICENSE
wonderpatch-0.1.0.dist-info/METADATA
wonderpatch-0.1.0.dist-info/WHEEL
wonderpatch-0.1.0.dist-info/top_level.txt
wonderpatch-0.1.0.dist-info/RECORD
