Metadata-Version: 2.1
Name: wonderpatch
Version: 0.1.0
Summary: A better patch tool for python test.
Home-page: https://github.com/kingronjan/wonderpatch
Author: kingronjan
Author-email: kingronjan@qq.com
Keywords: wonderpatch
Classifier: Development Status :: 2 - Pre-Alpha
Classifier: Intended Audience :: Developers
Classifier: Natural Language :: English
Classifier: Programming Language :: Python :: 3
Classifier: Programming Language :: Python :: 3.5
Classifier: Programming Language :: Python :: 3.6
Classifier: Programming Language :: Python :: 3.7
Classifier: Programming Language :: Python :: 3.8
Requires-Python: >=3.5
License-File: LICENSE
